<?xml version="1.0" ?>
<annotation>
<folder>PicALL</folder>
<filename>dog_77.jpg</filename>
<path>F:\xiaohuihui\4.YOLOV5\cat_dog_detection\cat_dog_datas\images\PicALL\dog_77.jpg</path>
<source>
    <database>Unknown</database>
</source>
<size>
    <width>500</width>
    <height>323</height>
    <depth>3</depth>
</size>

<segmented>0</segmented>
    <object>
    <name>dog</name>
    <pose>Unspecified</pose>
    <truncated>0</truncated>
    <difficult>0</difficult>
    <bndbox>
        <xmin>142</xmin>
        <ymin>37</ymin>
        <xmax>254</xmax>
        <ymax>137</ymax>
    </bndbox>
</object>
    <object>
    <name>dog</name>
    <pose>Unspecified</pose>
    <truncated>0</truncated>
    <difficult>0</difficult>
    <bndbox>
        <xmin>305</xmin>
        <ymin>38</ymin>
        <xmax>409</xmax>
        <ymax>130</ymax>
    </bndbox>
</object>
</annotation>
